drb_impl_json/__init__.py
drb_impl_json/_version.py
drb_impl_json/cortex.yml
drb_impl_json/json_node.py
drb_impl_json/json_node_factory.py
drb_impl_json-1.0.1.data/data/requirements.txt
drb_impl_json-1.0.1.dist-info/METADATA
drb_impl_json-1.0.1.dist-info/WHEEL
drb_impl_json-1.0.1.dist-info/entry_points.txt
drb_impl_json-1.0.1.dist-info/top_level.txt
drb_impl_json-1.0.1.dist-info/RECORD
