Metadata-Version: 2.1
Name: drb-impl-json
Version: 1.0.1
Summary: DRB json implementation
Home-page: https://gitlab.com/drb-python/impl/json
Author: GAEL Systems
Author-email: drb-python@gael.fr
License: UNKNOWN
Project-URL: Documentation, http://drb-python.gitlab.io/impl/json
Project-URL: Source, https://gitlab.com/drb-python/impl/json
Platform: UNKNOWN
Classifier: Programming Language :: Python :: 3.8
Classifier: License :: OSI Approved :: Apache Software License
Classifier: Operating System :: OS Independent
Requires-Python: >=3.8
Requires-Dist: drb (<1.1.0,>=1.0.1)
